jax_linear_operator/__init__.py
jax_linear_operator-0.0.0.dist-info/LICENSE
jax_linear_operator-0.0.0.dist-info/METADATA
jax_linear_operator-0.0.0.dist-info/WHEEL
jax_linear_operator-0.0.0.dist-info/top_level.txt
jax_linear_operator-0.0.0.dist-info/RECORD
